roborabbit/__init__.py
roborabbit/connection.py
roborabbit/logger.py
roborabbit/main.py
roborabbit/rmq.py
roborabbit/roborabbit.py
roborabbit-0.4.2.dist-info/entry_points.txt
roborabbit-0.4.2.dist-info/LICENSE
roborabbit-0.4.2.dist-info/WHEEL
roborabbit-0.4.2.dist-info/METADATA
roborabbit-0.4.2.dist-info/RECORD
