Metadata-Version: 2.1
Name: roborabbit
Version: 0.4.2
Summary: Set up your rabbit instance using a declarative yaml file.
Home-page: https://github.com/alairock/roborabbit
License: Apache-2.0
Author: Skyler Lewis
Author-email: skyler@hivewire.co
Requires-Python: >=3.9,<4.0
Classifier: License :: OSI Approved :: Apache Software License
Classifier: Programming Language :: Python :: 3
Classifier: Programming Language :: Python :: 3.10
Classifier: Programming Language :: Python :: 3.9
Requires-Dist: PyYAML (>=5.4,<6.0)
Requires-Dist: aio-pika (>=7.1,<8.0)
Requires-Dist: click (>=8.0,<9.0)
Project-URL: Documentation, https://github.com/alairock/roborabbit/blob/main/README.md
Project-URL: Repository, https://github.com/alairock/roborabbit
